get_gitlab_issues/__init__.py
get_gitlab_issues/main.py
get_gitlab_issues-2025.5.180909.dist-info/licenses/LICENSE
tests/__init__.py
tests/test_gitlab_functions.py
get_gitlab_issues-2025.5.180909.dist-info/METADATA
get_gitlab_issues-2025.5.180909.dist-info/WHEEL
get_gitlab_issues-2025.5.180909.dist-info/top_level.txt
get_gitlab_issues-2025.5.180909.dist-info/RECORD
